langchain_pgvec_textsearch/__init__.py
langchain_pgvec_textsearch/vectorstores/__init__.py
langchain_pgvec_textsearch/vectorstores/engine.py
langchain_pgvec_textsearch/vectorstores/filters.py
langchain_pgvec_textsearch/vectorstores/hybrid_search_config.py
langchain_pgvec_textsearch/vectorstores/indexes.py
langchain_pgvec_textsearch/vectorstores/pgvec_textsearch.py
langchain_pgvec_textsearch-0.1.3.dist-info/METADATA
langchain_pgvec_textsearch-0.1.3.dist-info/WHEEL
langchain_pgvec_textsearch-0.1.3.dist-info/licenses/LICENSE
langchain_pgvec_textsearch-0.1.3.dist-info/RECORD
