Metadata-Version: 2.4
Name: langchain-pgvec-textsearch
Version: 0.1.3
Summary: LangChain VectorStore for hybrid search with pgvector (dense) and pg_textsearch (BM25)
Author-email: id4thomas <id2thomas@gmail.com>
License: MIT
License-File: LICENSE
Keywords: bm25,hybrid-search,langchain,pg_textsearch,pgvector,postgresql,rrf,vectorstore
Classifier: Development Status :: 4 - Beta
Classifier: Intended Audience :: Developers
Classifier: License :: OSI Approved :: MIT License
Classifier: Programming Language :: Python :: 3
Classifier: Programming Language :: Python :: 3.9
Classifier: Programming Language :: Python :: 3.10
Classifier: Programming Language :: Python :: 3.11
Classifier: Programming Language :: Python :: 3.12
Classifier: Programming Language :: Python :: 3.13
Classifier: Topic :: Database
Classifier: Topic :: Scientific/Engineering :: Artificial Intelligence
Requires-Python: >=3.9
Requires-Dist: asyncpg>=0.29.0
Requires-Dist: langchain-core>=0.3.0
Requires-Dist: langchain-postgres>=0.0.16
Requires-Dist: numpy>=1.24.0
Requires-Dist: pgvector>=0.3.0
Requires-Dist: sqlalchemy>=2.0.0
